collageradiomics.py
collageradiomics-0.3.8.dist-info/LICENSE
collageradiomics-0.3.8.dist-info/METADATA
collageradiomics-0.3.8.dist-info/WHEEL
collageradiomics-0.3.8.dist-info/top_level.txt
collageradiomics-0.3.8.dist-info/RECORD
