Metadata-Version: 2.1
Name: collageradiomics
Version: 0.3.8
Summary: Python implementation of COLLAGE texture features from BRIC & INVENTLAB.
Home-page: https://github.com/ccipd/collageradiomics
Author: ThetaTech
Author-email: robert.toth@thetatech.ai
License: UNKNOWN
Project-URL: Docker Examples, https://hub.docker.com/repository/docker/ccipd/collageradiomics-examples
Project-URL: Docker Module, https://hub.docker.com/repository/docker/ccipd/collageradiomics-pip
Project-URL: Github, https://github.com/ccipd/collageradiomics
Keywords: radiomics cancerimaging medicalresearch computationalimaging
Platform: UNKNOWN
Classifier: Development Status :: 3 - Alpha
Classifier: Intended Audience :: Science/Research
Classifier: Intended Audience :: Developers
Classifier: License :: OSI Approved :: BSD License
Classifier: Operating System :: OS Independent
Classifier: Operating System :: POSIX :: Linux
Classifier: Operating System :: Microsoft :: Windows :: Windows 10
Classifier: Operating System :: MacOS
Classifier: Programming Language :: Python :: 3
Classifier: Topic :: Scientific/Engineering :: Bio-Informatics
Requires-Python: >=3.6
Requires-Dist: mahotas (==1.4.13)
Requires-Dist: numpy (>=1.21.6)
Requires-Dist: Pillow (==9.2.0)
Requires-Dist: scikit-build (>=0.15.0)
Requires-Dist: scikit-image (>=0.19.3)
Requires-Dist: scipy (>=1.7.3)
Requires-Dist: pydicom (>=2.3.0)
Requires-Dist: sklearn
